flashcardpro/__init__.py
flashcardpro/__main__.py
flashcardpro-0.1.0.dist-info/METADATA
flashcardpro-0.1.0.dist-info/WHEEL
flashcardpro-0.1.0.dist-info/entry_points.txt
flashcardpro-0.1.0.dist-info/top_level.txt
flashcardpro-0.1.0.dist-info/RECORD
