Metadata-Version: 2.1
Name: flashcardpro
Version: 0.1.0
Summary: A flashcard creation and learning application
Home-page: https://github.com/fuhma0q0/flashcardpro
Author: Your Name
Author-email: your.email@example.com
Classifier: Programming Language :: Python :: 3
Classifier: License :: OSI Approved :: MIT License
Classifier: Operating System :: OS Independent
Requires-Python: >=3.6
Requires-Dist: Django <4.0,>=3.0
Requires-Dist: djangorestframework
Requires-Dist: django-cors-headers
